{
  "id": "EG-NOT-APPLICABLE",
  "title": "Test Grant: Not Asked, Not Applicable",
  "description": "An example grant where the funder did not ask any questions because they are not applicable",
  "currency": "GBP",
  "amountAwarded": 1000,
  "awardDate": "2021-01-01T00:00:00Z",
  "fundingOrganization": [
    {
      "id": "example-funder-001",
      "name": "Example Funding Organisation"
    }
  ],
  "recipientOrganization": [
    {
      "id": "example-recipient-001",
      "name": "Example Recipient Organisation"
    }
  ],
  "deiDetails": {
    "leadership": {
      "askedStatus": "AS100"
    },
    "mission": {
      "askedStatus": "AS100"
    },
    "project": {
      "askedStatus": "AS100"
    }
  }
}
